pytorch_spiking/__init__.py
pytorch_spiking/functional.py
pytorch_spiking/modules.py
pytorch_spiking/version.py
pytorch_spiking/tests/test_modules.py
pytorch_spiking-0.1.0.dist-info/LICENSE.rst
pytorch_spiking-0.1.0.dist-info/METADATA
pytorch_spiking-0.1.0.dist-info/WHEEL
pytorch_spiking-0.1.0.dist-info/top_level.txt
pytorch_spiking-0.1.0.dist-info/RECORD
